[{"name": {"title": "", "first": "Madeline", "middle": "", "last": "Haberl", "suffix": "", "nickname": "", "original": "Madeline Haberl"}, "location": {"zip_code": "48225", "zip_code_type": "STANDARD", "active": true, "city": "Harper Woods", "acceptable_cities": ["Detroit"], "unacceptable_cities": [], "state": "MI", "county": "Wayne County", "timezone": "America/Detroit", "area_codes": [], "world_region": "NA", "country": "US", "lat": "42.4361", "long": "-82.9317"}, "birth": {"day": 14, "month": 5, "year": 1926, "original": "May 14 1926"}, "death": {"day": 9, "month": 7, "year": 2007, "original": "July 9 2007"}}, {"name": {"title": "", "first": "James", "middle": "L", "last": "Mason", "suffix": "", "nickname": "", "original": "James L Mason"}, "location": {"zip_code": "48225", "zip_code_type": "STANDARD", "active": true, "city": "Harper Woods", "acceptable_cities": ["Detroit"], "unacceptable_cities": [], "state": "MI", "county": "Wayne County", "timezone": "America/Detroit", "area_codes": [], "world_region": "NA", "country": "US", "lat": "42.4361", "long": "-82.9317"}, "birth": {"day": 9, "month": 11, "year": 1926, "original": "Nov 9 1926"}, "death": {"day": 10, "month": 1, "year": 2007, "original": "Jan 10 2007"}}, {"name": {"title": "", "first": "Margaret", "middle": "M", "last": "Ghesquiere", "suffix": "", "nickname": "", "original": "Margaret M Ghesquiere"}, "location": {"zip_code": "48225", "zip_code_type": "STANDARD", "active": true, "city": "Harper Woods", "acceptable_cities": ["Detroit"], "unacceptable_cities": [], "state": "MI", "county": "Wayne County", "timezone": "America/Detroit", "area_codes": [], "world_region": "NA", "country": "US", "lat": "42.4361", "long": "-82.9317"}, "birth": {"day": 18, "month": 3, "year": 1926, "original": "Mar 18 1926"}, "death": {"day": 27, "month": 3, "year": 2007, "original": "Mar 27 2007"}}, {"name": {"title": "", "first": "Harold", "middle": "A", "last": "Brisson", "suffix": "", "nickname": "", "original": "Harold A Brisson"}, "location": {"zip_code": "48225", "zip_code_type": "STANDARD", "active": true, "city": "Harper Woods", "acceptable_cities": ["Detroit"], "unacceptable_cities": [], "state": "MI", "county": "Wayne County", "timezone": "America/Detroit", "area_codes": [], "world_region": "NA", "country": "US", "lat": "42.4361", "long": "-82.9317"}, "birth": {"day": 26, "month": 8, "year": 1926, "original": "Aug 26 1926"}, "death": {"day": 18, "month": 4, "year": 2007, "original": "Apr 18 2007"}}]