[{"name": {"title": "", "first": "Ernest", "middle": "F", "last": "Swek", "suffix": "", "nickname": "", "original": "Ernest F Swek"}, "location": {"zip_code": "48146", "zip_code_type": "STANDARD", "active": true, "city": "Lincoln Park", "acceptable_cities": [], "unacceptable_cities": [], "state": "MI", "county": "Wayne County", "timezone": "America/Detroit", "area_codes": ["313"], "world_region": "NA", "country": "US", "lat": "42.2462", "long": "-83.1821"}, "birth": {"day": 1, "month": 5, "year": 1935, "original": "May 1 1935"}, "death": {"day": 13, "month": 1, "year": 1993, "original": "Jan 1993"}}, {"name": {"title": "", "first": "Rhoe", "middle": "Jean H", "last": "Krolikiewicz", "suffix": "", "nickname": "", "original": "Rhoe Jean H Krolikiewicz"}, "location": {"zip_code": "48146", "zip_code_type": "STANDARD", "active": true, "city": "Lincoln Park", "acceptable_cities": [], "unacceptable_cities": [], "state": "MI", "county": "Wayne County", "timezone": "America/Detroit", "area_codes": ["313"], "world_region": "NA", "country": "US", "lat": "42.2462", "long": "-83.1821"}, "birth": {"day": 14, "month": 4, "year": 1935, "original": "Apr 14 1935"}, "death": {"day": 18, "month": 12, "year": 1993, "original": "Dec 18 1993"}}, {"name": {"title": "", "first": "Dorothy", "middle": "J", "last": "Dudzic", "suffix": "", "nickname": "", "original": "Dorothy J Dudzic"}, "location": {"zip_code": "48146", "zip_code_type": "STANDARD", "active": true, "city": "Lincoln Park", "acceptable_cities": [], "unacceptable_cities": [], "state": "MI", "county": "Wayne County", "timezone": "America/Detroit", "area_codes": ["313"], "world_region": "NA", "country": "US", "lat": "42.2462", "long": "-83.1821"}, "birth": {"day": 13, "month": 8, "year": 1935, "original": "Aug 13 1935"}, "death": {"day": 29, "month": 6, "year": 1993, "original": "June 29 1993"}}]