[{"name": {"title": "", "first": "Julius", "middle": "", "last": "Gantt", "suffix": "III", "nickname": "", "original": "Julius Gantt III"}, "location": {"zip_code": "48204", "zip_code_type": "STANDARD", "active": true, "city": "Detroit", "acceptable_cities": [], "unacceptable_cities": [], "state": "MI", "county": "Wayne County", "timezone": "America/Detroit", "area_codes": ["313"], "world_region": "NA", "country": "US", "lat": "42.3678", "long": "-83.1390"}, "birth": {"day": 20, "month": 3, "year": 1949, "original": "Mar 20 1949"}, "death": {"day": 9, "month": 6, "year": 1997, "original": "June 9 1997"}}, {"name": {"title": "", "first": "Larry", "middle": "", "last": "Stowers", "suffix": "", "nickname": "", "original": "Larry Stowers"}, "location": {"zip_code": "48204", "zip_code_type": "STANDARD", "active": true, "city": "Detroit", "acceptable_cities": [], "unacceptable_cities": [], "state": "MI", "county": "Wayne County", "timezone": "America/Detroit", "area_codes": ["313"], "world_region": "NA", "country": "US", "lat": "42.3678", "long": "-83.1390"}, "birth": {"day": 2, "month": 2, "year": 1949, "original": "Feb 2 1949"}, "death": {"day": 6, "month": 9, "year": 1997, "original": "Sep 6 1997"}}, {"name": {"title": "", "first": "Lincoln", "middle": "M", "last": "Burns", "suffix": "", "nickname": "", "original": "Lincoln M Burns"}, "location": {"zip_code": "48204", "zip_code_type": "STANDARD", "active": true, "city": "Detroit", "acceptable_cities": [], "unacceptable_cities": [], "state": "MI", "county": "Wayne County", "timezone": "America/Detroit", "area_codes": ["313"], "world_region": "NA", "country": "US", "lat": "42.3678", "long": "-83.1390"}, "birth": {"day": 4, "month": 8, "year": 1949, "original": "Aug 4 1949"}, "death": {"day": 24, "month": 2, "year": 1997, "original": "Feb 24 1997"}}, {"name": {"title": "", "first": "Larry", "middle": "", "last": "Lewis", "suffix": "", "nickname": "", "original": "Larry Lewis"}, "location": {"zip_code": "48204", "zip_code_type": "STANDARD", "active": true, "city": "Detroit", "acceptable_cities": [], "unacceptable_cities": [], "state": "MI", "county": "Wayne County", "timezone": "America/Detroit", "area_codes": ["313"], "world_region": "NA", "country": "US", "lat": "42.3678", "long": "-83.1390"}, "birth": {"day": 5, "month": 9, "year": 1949, "original": "Sep 5 1949"}, "death": {"day": 13, "month": 5, "year": 1997, "original": "May 13 1997"}}, {"name": {"title": "", "first": "Jerry", "middle": "", "last": "Matthews", "suffix": "", "nickname": "", "original": "Jerry Matthews"}, "location": {"zip_code": "48204", "zip_code_type": "STANDARD", "active": true, "city": "Detroit", "acceptable_cities": [], "unacceptable_cities": [], "state": "MI", "county": "Wayne County", "timezone": "America/Detroit", "area_codes": ["313"], "world_region": "NA", "country": "US", "lat": "42.3678", "long": "-83.1390"}, "birth": {"day": 19, "month": 7, "year": 1949, "original": "July 19 1949"}, "death": {"day": 9, "month": 3, "year": 1997, "original": "Mar 9 1997"}}]