[{"name": {"title": "", "first": "Daniel", "middle": "E", "last": "Stroud", "suffix": "", "nickname": "", "original": "Daniel E Stroud"}, "location": {"zip_code": "48201", "zip_code_type": "STANDARD", "active": true, "city": "Detroit", "acceptable_cities": [], "unacceptable_cities": [], "state": "MI", "county": "Wayne County", "timezone": "America/Detroit", "area_codes": ["248", "313", "586", "734"], "world_region": "NA", "country": "US", "lat": "42.3462", "long": "-83.0606"}, "birth": {"day": 23, "month": 9, "year": 1905, "original": "Sep 23 1905"}, "death": {"day": 26, "month": 3, "year": 1989, "original": "Mar 26 1989"}}, {"name": {"title": "", "first": "Clarence", "middle": "B", "last": "Gardner", "suffix": "", "nickname": "", "original": "Clarence B Gardner"}, "location": {"zip_code": "48201", "zip_code_type": "STANDARD", "active": true, "city": "Detroit", "acceptable_cities": [], "unacceptable_cities": [], "state": "MI", "county": "Wayne County", "timezone": "America/Detroit", "area_codes": ["248", "313", "586", "734"], "world_region": "NA", "country": "US", "lat": "42.3462", "long": "-83.0606"}, "birth": {"day": 5, "month": 10, "year": 1905, "original": "Oct 5 1905"}, "death": {"day": 22, "month": 8, "year": 1989, "original": "Aug 22 1989"}}, {"name": {"title": "", "first": "Bennie", "middle": "W", "last": "Vaughn", "suffix": "", "nickname": "", "original": "Bennie W Vaughn"}, "location": {"zip_code": "48201", "zip_code_type": "STANDARD", "active": true, "city": "Detroit", "acceptable_cities": [], "unacceptable_cities": [], "state": "MI", "county": "Wayne County", "timezone": "America/Detroit", "area_codes": ["248", "313", "586", "734"], "world_region": "NA", "country": "US", "lat": "42.3462", "long": "-83.0606"}, "birth": {"day": 16, "month": 4, "year": 1905, "original": "Apr 1905"}, "death": {"day": 15, "month": 9, "year": 1989, "original": "Sep 15 1989"}}, {"name": {"title": "", "first": "Fred", "middle": "D", "last": "Sullivan", "suffix": "", "nickname": "", "original": "Fred D Sullivan"}, "location": {"zip_code": "48201", "zip_code_type": "STANDARD", "active": true, "city": "Detroit", "acceptable_cities": [], "unacceptable_cities": [], "state": "MI", "county": "Wayne County", "timezone": "America/Detroit", "area_codes": ["248", "313", "586", "734"], "world_region": "NA", "country": "US", "lat": "42.3462", "long": "-83.0606"}, "birth": {"day": 20, "month": 6, "year": 1905, "original": "June 20 1905"}, "death": {"day": 3, "month": 10, "year": 1989, "original": "Oct 3 1989"}}, {"name": {"title": "", "first": "Michael", "middle": "J", "last": "Morris", "suffix": "", "nickname": "", "original": "Michael J Morris"}, "location": {"zip_code": "48201", "zip_code_type": "STANDARD", "active": true, "city": "Detroit", "acceptable_cities": [], "unacceptable_cities": [], "state": "MI", "county": "Wayne County", "timezone": "America/Detroit", "area_codes": ["248", "313", "586", "734"], "world_region": "NA", "country": "US", "lat": "42.3462", "long": "-83.0606"}, "birth": {"day": 18, "month": 7, "year": 1905, "original": "July 18 1905"}, "death": {"day": 9, "month": 10, "year": 1989, "original": "Oct 9 1989"}}, {"name": {"title": "", "first": "Benjamin", "middle": "F", "last": "Lewis", "suffix": "", "nickname": "", "original": "Benjamin F Lewis"}, "location": {"zip_code": "48201", "zip_code_type": "STANDARD", "active": true, "city": "Detroit", "acceptable_cities": [], "unacceptable_cities": [], "state": "MI", "county": "Wayne County", "timezone": "America/Detroit", "area_codes": ["248", "313", "586", "734"], "world_region": "NA", "country": "US", "lat": "42.3462", "long": "-83.0606"}, "birth": {"day": 7, "month": 11, "year": 1905, "original": "Nov 7 1905"}, "death": {"day": 25, "month": 2, "year": 1989, "original": "Feb 25 1989"}}, {"name": {"title": "", "first": "Helen", "middle": "", "last": "Thomas", "suffix": "", "nickname": "", "original": "Helen Thomas"}, "location": {"zip_code": "48201", "zip_code_type": "STANDARD", "active": true, "city": "Detroit", "acceptable_cities": [], "unacceptable_cities": [], "state": "MI", "county": "Wayne County", "timezone": "America/Detroit", "area_codes": ["248", "313", "586", "734"], "world_region": "NA", "country": "US", "lat": "42.3462", "long": "-83.0606"}, "birth": {"day": 1, "month": 3, "year": 1905, "original": "Mar 1 1905"}, "death": {"day": 6, "month": 5, "year": 1989, "original": "May 6 1989"}}]