[{"name": {"title": "", "first": "Gordon", "middle": "", "last": "Jones", "suffix": "", "nickname": "", "original": "Gordon Jones"}, "location": {"zip_code": "48127", "zip_code_type": "STANDARD", "active": true, "city": "Dearborn Heights", "acceptable_cities": ["Dearborn Hts"], "unacceptable_cities": [], "state": "MI", "county": "Wayne County", "timezone": "America/Detroit", "area_codes": ["313"], "world_region": "NA", "country": "US", "lat": "42.3344", "long": "-83.2739"}, "birth": {"day": 7, "month": 12, "year": 1907, "original": "Dec 7 1907"}, "death": {"day": 13, "month": 6, "year": 1977, "original": "June 1977"}}, {"name": {"title": "", "first": "Clara", "middle": "", "last": "Bizek", "suffix": "", "nickname": "", "original": "Clara Bizek"}, "location": {"zip_code": "48127", "zip_code_type": "STANDARD", "active": true, "city": "Dearborn Heights", "acceptable_cities": ["Dearborn Hts"], "unacceptable_cities": [], "state": "MI", "county": "Wayne County", "timezone": "America/Detroit", "area_codes": ["313"], "world_region": "NA", "country": "US", "lat": "42.3344", "long": "-83.2739"}, "birth": {"day": 21, "month": 3, "year": 1907, "original": "Mar 21 1907"}, "death": {"day": 13, "month": 7, "year": 1977, "original": "July 1977"}}, {"name": {"title": "", "first": "James", "middle": "", "last": "Stapleton", "suffix": "", "nickname": "", "original": "James Stapleton"}, "location": {"zip_code": "48127", "zip_code_type": "STANDARD", "active": true, "city": "Dearborn Heights", "acceptable_cities": ["Dearborn Hts"], "unacceptable_cities": [], "state": "MI", "county": "Wayne County", "timezone": "America/Detroit", "area_codes": ["313"], "world_region": "NA", "country": "US", "lat": "42.3344", "long": "-83.2739"}, "birth": {"day": 10, "month": 3, "year": 1907, "original": "Mar 10 1907"}, "death": {"day": 13, "month": 4, "year": 1977, "original": "Apr 1977"}}, {"name": {"title": "", "first": "Betty", "middle": "", "last": "Gall", "suffix": "", "nickname": "", "original": "Betty Gall"}, "location": {"zip_code": "48127", "zip_code_type": "STANDARD", "active": true, "city": "Dearborn Heights", "acceptable_cities": ["Dearborn Hts"], "unacceptable_cities": [], "state": "MI", "county": "Wayne County", "timezone": "America/Detroit", "area_codes": ["313"], "world_region": "NA", "country": "US", "lat": "42.3344", "long": "-83.2739"}, "birth": {"day": 17, "month": 7, "year": 1907, "original": "July 17 1907"}, "death": {"day": 13, "month": 10, "year": 1977, "original": "Oct 1977"}}, {"name": {"title": "", "first": "John", "middle": "", "last": "Rose", "suffix": "", "nickname": "", "original": "John Rose"}, "location": {"zip_code": "48127", "zip_code_type": "STANDARD", "active": true, "city": "Dearborn Heights", "acceptable_cities": ["Dearborn Hts"], "unacceptable_cities": [], "state": "MI", "county": "Wayne County", "timezone": "America/Detroit", "area_codes": ["313"], "world_region": "NA", "country": "US", "lat": "42.3344", "long": "-83.2739"}, "birth": {"day": 29, "month": 11, "year": 1907, "original": "Nov 29 1907"}, "death": {"day": 13, "month": 5, "year": 1977, "original": "May 1977"}}, {"name": {"title": "", "first": "Alphonse", "middle": "", "last": "Klach", "suffix": "", "nickname": "", "original": "Alphonse Klach"}, "location": {"zip_code": "48127", "zip_code_type": "STANDARD", "active": true, "city": "Dearborn Heights", "acceptable_cities": ["Dearborn Hts"], "unacceptable_cities": [], "state": "MI", "county": "Wayne County", "timezone": "America/Detroit", "area_codes": ["313"], "world_region": "NA", "country": "US", "lat": "42.3344", "long": "-83.2739"}, "birth": {"day": 10, "month": 4, "year": 1907, "original": "Apr 10 1907"}, "death": {"day": 13, "month": 6, "year": 1977, "original": "June 1977"}}, {"name": {"title": "", "first": "Walter", "middle": "", "last": "Cornell", "suffix": "", "nickname": "", "original": "Walter Cornell"}, "location": {"zip_code": "48127", "zip_code_type": "STANDARD", "active": true, "city": "Dearborn Heights", "acceptable_cities": ["Dearborn Hts"], "unacceptable_cities": [], "state": "MI", "county": "Wayne County", "timezone": "America/Detroit", "area_codes": ["313"], "world_region": "NA", "country": "US", "lat": "42.3344", "long": "-83.2739"}, "birth": {"day": 17, "month": 2, "year": 1907, "original": "Feb 17 1907"}, "death": {"day": 13, "month": 6, "year": 1977, "original": "June 1977"}}, {"name": {"title": "", "first": "Alexander", "middle": "", "last": "Rust", "suffix": "", "nickname": "", "original": "Alexander Rust"}, "location": {"zip_code": "48127", "zip_code_type": "STANDARD", "active": true, "city": "Dearborn Heights", "acceptable_cities": ["Dearborn Hts"], "unacceptable_cities": [], "state": "MI", "county": "Wayne County", "timezone": "America/Detroit", "area_codes": ["313"], "world_region": "NA", "country": "US", "lat": "42.3344", "long": "-83.2739"}, "birth": {"day": 27, "month": 10, "year": 1907, "original": "Oct 27 1907"}, "death": {"day": 13, "month": 1, "year": 1977, "original": "Jan 1977"}}, {"name": {"title": "", "first": "William", "middle": "", "last": "Sevakis", "suffix": "", "nickname": "", "original": "William Sevakis"}, "location": {"zip_code": "48127", "zip_code_type": "STANDARD", "active": true, "city": "Dearborn Heights", "acceptable_cities": ["Dearborn Hts"], "unacceptable_cities": [], "state": "MI", "county": "Wayne County", "timezone": "America/Detroit", "area_codes": ["313"], "world_region": "NA", "country": "US", "lat": "42.3344", "long": "-83.2739"}, "birth": {"day": 17, "month": 6, "year": 1907, "original": "June 17 1907"}, "death": {"day": 13, "month": 11, "year": 1977, "original": "Nov 1977"}}, {"name": {"title": "", "first": "Regina", "middle": "", "last": "Kopmeyer", "suffix": "", "nickname": "", "original": "Regina Kopmeyer"}, "location": {"zip_code": "48127", "zip_code_type": "STANDARD", "active": true, "city": "Dearborn Heights", "acceptable_cities": ["Dearborn Hts"], "unacceptable_cities": [], "state": "MI", "county": "Wayne County", "timezone": "America/Detroit", "area_codes": ["313"], "world_region": "NA", "country": "US", "lat": "42.3344", "long": "-83.2739"}, "birth": {"day": 15, "month": 10, "year": 1907, "original": "Oct 15 1907"}, "death": {"day": 13, "month": 7, "year": 1977, "original": "July 1977"}}, {"name": {"title": "", "first": "Carl", "middle": "", "last": "Pekula", "suffix": "", "nickname": "", "original": "Carl Pekula"}, "location": {"zip_code": "48127", "zip_code_type": "STANDARD", "active": true, "city": "Dearborn Heights", "acceptable_cities": ["Dearborn Hts"], "unacceptable_cities": [], "state": "MI", "county": "Wayne County", "timezone": "America/Detroit", "area_codes": ["313"], "world_region": "NA", "country": "US", "lat": "42.3344", "long": "-83.2739"}, "birth": {"day": 15, "month": 7, "year": 1907, "original": "July 15 1907"}, "death": {"day": 13, "month": 12, "year": 1977, "original": "Dec 1977"}}]