[{"name": {"title": "", "first": "John", "middle": "", "last": "Mysiewicz", "suffix": "", "nickname": "", "original": "John Mysiewicz"}, "location": {"zip_code": "48126", "zip_code_type": "STANDARD", "active": true, "city": "Dearborn", "acceptable_cities": [], "unacceptable_cities": [], "state": "MI", "county": "Wayne County", "timezone": "America/Detroit", "area_codes": ["313"], "world_region": "NA", "country": "US", "lat": "42.3274", "long": "-83.1910"}, "birth": {"day": 20, "month": 8, "year": 1913, "original": "Aug 20 1913"}, "death": {"day": 13, "month": 11, "year": 1971, "original": "Nov 1971"}}, {"name": {"title": "", "first": "E", "middle": "", "last": "Spaven", "suffix": "", "nickname": "", "original": "E Spaven"}, "location": {"zip_code": "48126", "zip_code_type": "STANDARD", "active": true, "city": "Dearborn", "acceptable_cities": [], "unacceptable_cities": [], "state": "MI", "county": "Wayne County", "timezone": "America/Detroit", "area_codes": ["313"], "world_region": "NA", "country": "US", "lat": "42.3274", "long": "-83.1910"}, "birth": {"day": 14, "month": 12, "year": 1913, "original": "Dec 14 1913"}, "death": {"day": 13, "month": 9, "year": 1971, "original": "Sep 1971"}}, {"name": {"title": "", "first": "Ernest", "middle": "", "last": "Blye", "suffix": "", "nickname": "", "original": "Ernest Blye"}, "location": {"zip_code": "48126", "zip_code_type": "STANDARD", "active": true, "city": "Dearborn", "acceptable_cities": [], "unacceptable_cities": [], "state": "MI", "county": "Wayne County", "timezone": "America/Detroit", "area_codes": ["313"], "world_region": "NA", "country": "US", "lat": "42.3274", "long": "-83.1910"}, "birth": {"day": 4, "month": 8, "year": 1913, "original": "Aug 4 1913"}, "death": {"day": 13, "month": 12, "year": 1971, "original": "Dec 1971"}}, {"name": {"title": "", "first": "George", "middle": "", "last": "Price", "suffix": "", "nickname": "", "original": "George Price"}, "location": {"zip_code": "48126", "zip_code_type": "STANDARD", "active": true, "city": "Dearborn", "acceptable_cities": [], "unacceptable_cities": [], "state": "MI", "county": "Wayne County", "timezone": "America/Detroit", "area_codes": ["313"], "world_region": "NA", "country": "US", "lat": "42.3274", "long": "-83.1910"}, "birth": {"day": 12, "month": 2, "year": 1913, "original": "Feb 12 1913"}, "death": {"day": 13, "month": 4, "year": 1971, "original": "Apr 1971"}}]