[{"name": {"title": "", "first": "Alma", "middle": "L", "last": "Seaborn", "suffix": "", "nickname": "", "original": "Alma L Seaborn"}, "location": {"zip_code": "48227", "zip_code_type": "STANDARD", "active": true, "city": "Detroit", "acceptable_cities": [], "unacceptable_cities": [], "state": "MI", "county": "Wayne County", "timezone": "America/Detroit", "area_codes": ["313"], "world_region": "NA", "country": "US", "lat": "42.3873", "long": "-83.1933"}, "birth": {"day": 6, "month": 3, "year": 1937, "original": "Mar 6 1937"}, "death": {"day": 30, "month": 12, "year": 1996, "original": "Dec 30 1996"}}, {"name": {"title": "", "first": "Harold", "middle": "", "last": "Mitchell", "suffix": "", "nickname": "", "original": "Harold Mitchell"}, "location": {"zip_code": "48227", "zip_code_type": "STANDARD", "active": true, "city": "Detroit", "acceptable_cities": [], "unacceptable_cities": [], "state": "MI", "county": "Wayne County", "timezone": "America/Detroit", "area_codes": ["313"], "world_region": "NA", "country": "US", "lat": "42.3873", "long": "-83.1933"}, "birth": {"day": 22, "month": 11, "year": 1937, "original": "Nov 22 1937"}, "death": {"day": 13, "month": 4, "year": 1996, "original": "Apr 13 1996"}}, {"name": {"title": "", "first": "Mary", "middle": "E", "last": "Pacheco", "suffix": "", "nickname": "", "original": "Mary E Pacheco"}, "location": {"zip_code": "48227", "zip_code_type": "STANDARD", "active": true, "city": "Detroit", "acceptable_cities": [], "unacceptable_cities": [], "state": "MI", "county": "Wayne County", "timezone": "America/Detroit", "area_codes": ["313"], "world_region": "NA", "country": "US", "lat": "42.3873", "long": "-83.1933"}, "birth": {"day": 22, "month": 8, "year": 1937, "original": "Aug 22 1937"}, "death": {"day": 20, "month": 12, "year": 1996, "original": "Dec 20 1996"}}, {"name": {"title": "", "first": "Lessie", "middle": "", "last": "Robertson", "suffix": "", "nickname": "", "original": "Lessie Robertson"}, "location": {"zip_code": "48227", "zip_code_type": "STANDARD", "active": true, "city": "Detroit", "acceptable_cities": [], "unacceptable_cities": [], "state": "MI", "county": "Wayne County", "timezone": "America/Detroit", "area_codes": ["313"], "world_region": "NA", "country": "US", "lat": "42.3873", "long": "-83.1933"}, "birth": {"day": 17, "month": 4, "year": 1937, "original": "Apr 17 1937"}, "death": {"day": 18, "month": 4, "year": 1996, "original": "Apr 18 1996"}}]