{"name": {"title": "", "first": "Stanley", "middle": "", "last": "Beger", "suffix": "", "nickname": "", "original": "Stanley Beger"}, "location": {"zip_code": "48201", "zip_code_type": "STANDARD", "active": true, "city": "Detroit", "acceptable_cities": [], "unacceptable_cities": [], "state": "MI", "county": "Wayne County", "timezone": "America/Detroit", "area_codes": ["248", "313", "586", "734"], "world_region": "NA", "country": "US", "lat": "42.3462", "long": "-83.0606"}, "birth": {"day": 19, "month": 8, "year": 1900, "original": "Aug 19 1900"}, "death": {"day": 12, "month": 7, "year": 1967, "original": "July 1967"}}