{"name": {"title": "", "first": "Joseph", "middle": "S", "last": "Watson", "suffix": "", "nickname": "", "original": "Joseph S Watson"}, "location": {"zip_code": "48195", "zip_code_type": "STANDARD", "active": true, "city": "Southgate", "acceptable_cities": [], "unacceptable_cities": [], "state": "MI", "county": "Wayne County", "timezone": "America/Detroit", "area_codes": [], "world_region": "NA", "country": "US", "lat": "42.2061", "long": "-83.2047"}, "birth": {"day": 18, "month": 6, "year": 1940, "original": "June 18 1940"}, "death": {"day": 23, "month": 5, "year": 2005, "original": "May 23 2005"}}