{"name": {"title": "", "first": "Arthur", "middle": "O", "last": "Autio", "suffix": "", "nickname": "", "original": "Arthur O Autio"}, "location": {"zip_code": "48239", "zip_code_type": "STANDARD", "active": true, "city": "Redford", "acceptable_cities": ["Detroit"], "unacceptable_cities": ["Redford Twp"], "state": "MI", "county": "Wayne County", "timezone": "America/Detroit", "area_codes": ["313"], "world_region": "NA", "country": "US", "lat": "42.3745", "long": "-83.2808"}, "birth": {"day": 27, "month": 3, "year": 1924, "original": "Mar 27 1924"}, "death": {"day": 20, "month": 9, "year": 2006, "original": "Sep 20 2006"}}