[{"name": {"title": "", "first": "Willie", "middle": "", "last": "Rice", "suffix": "", "nickname": "", "original": "Willie Rice"}, "location": {"zip_code": "48202", "zip_code_type": "STANDARD", "active": true, "city": "Detroit", "acceptable_cities": [], "unacceptable_cities": [], "state": "MI", "county": "Wayne County", "timezone": "America/Detroit", "area_codes": ["313"], "world_region": "NA", "country": "US", "lat": "42.3744", "long": "-83.0775"}, "birth": {"day": 25, "month": 5, "year": 1921, "original": "May 25 1921"}, "death": {"day": 21, "month": 1, "year": 1993, "original": "Jan 21 1993"}}, {"name": {"title": "", "first": "Miguel", "middle": "A", "last": "Zarate", "suffix": "", "nickname": "", "original": "Miguel A Zarate"}, "location": {"zip_code": "48202", "zip_code_type": "STANDARD", "active": true, "city": "Detroit", "acceptable_cities": [], "unacceptable_cities": [], "state": "MI", "county": "Wayne County", "timezone": "America/Detroit", "area_codes": ["313"], "world_region": "NA", "country": "US", "lat": "42.3744", "long": "-83.0775"}, "birth": {"day": 21, "month": 1, "year": 1921, "original": "Jan 21 1921"}, "death": {"day": 13, "month": 1, "year": 1993, "original": "Jan 1993"}}, {"name": {"title": "", "first": "Ruth", "middle": "", "last": "Ferrell", "suffix": "", "nickname": "", "original": "Ruth Ferrell"}, "location": {"zip_code": "48202", "zip_code_type": "STANDARD", "active": true, "city": "Detroit", "acceptable_cities": [], "unacceptable_cities": [], "state": "MI", "county": "Wayne County", "timezone": "America/Detroit", "area_codes": ["313"], "world_region": "NA", "country": "US", "lat": "42.3744", "long": "-83.0775"}, "birth": {"day": 30, "month": 8, "year": 1921, "original": "Aug 30 1921"}, "death": {"day": 13, "month": 5, "year": 1993, "original": "May 1993"}}, {"name": {"title": "", "first": "Mimmie", "middle": "L", "last": "Talley", "suffix": "", "nickname": "", "original": "Mimmie L Talley"}, "location": {"zip_code": "48202", "zip_code_type": "STANDARD", "active": true, "city": "Detroit", "acceptable_cities": [], "unacceptable_cities": [], "state": "MI", "county": "Wayne County", "timezone": "America/Detroit", "area_codes": ["313"], "world_region": "NA", "country": "US", "lat": "42.3744", "long": "-83.0775"}, "birth": {"day": 18, "month": 12, "year": 1921, "original": "Dec 18 1921"}, "death": {"day": 15, "month": 9, "year": 1993, "original": "Sep 15 1993"}}, {"name": {"title": "", "first": "Virtia", "middle": "", "last": "White", "suffix": "", "nickname": "", "original": "Virtia White"}, "location": {"zip_code": "48202", "zip_code_type": "STANDARD", "active": true, "city": "Detroit", "acceptable_cities": [], "unacceptable_cities": [], "state": "MI", "county": "Wayne County", "timezone": "America/Detroit", "area_codes": ["313"], "world_region": "NA", "country": "US", "lat": "42.3744", "long": "-83.0775"}, "birth": {"day": 6, "month": 5, "year": 1921, "original": "May 6 1921"}, "death": {"day": 13, "month": 8, "year": 1993, "original": "Aug 1993"}}, {"name": {"title": "", "first": "Gladys", "middle": "", "last": "Robinson", "suffix": "", "nickname": "", "original": "Gladys Robinson"}, "location": {"zip_code": "48202", "zip_code_type": "STANDARD", "active": true, "city": "Detroit", "acceptable_cities": [], "unacceptable_cities": [], "state": "MI", "county": "Wayne County", "timezone": "America/Detroit", "area_codes": ["313"], "world_region": "NA", "country": "US", "lat": "42.3744", "long": "-83.0775"}, "birth": {"day": 19, "month": 3, "year": 1921, "original": "Mar 19 1921"}, "death": {"day": 13, "month": 6, "year": 1993, "original": "June 1993"}}, {"name": {"title": "", "first": "John", "middle": "E", "last": "Wilson", "suffix": "", "nickname": "", "original": "John E Wilson"}, "location": {"zip_code": "48202", "zip_code_type": "STANDARD", "active": true, "city": "Detroit", "acceptable_cities": [], "unacceptable_cities": [], "state": "MI", "county": "Wayne County", "timezone": "America/Detroit", "area_codes": ["313"], "world_region": "NA", "country": "US", "lat": "42.3744", "long": "-83.0775"}, "birth": {"day": 27, "month": 1, "year": 1921, "original": "Jan 27 1921"}, "death": {"day": 17, "month": 3, "year": 1993, "original": "Mar 17 1993"}}]