[{"name": {"title": "", "first": "Anderson", "middle": "", "last": "McPherson", "suffix": "", "nickname": "", "original": "Anderson McPherson"}, "location": {"zip_code": "48223", "zip_code_type": "STANDARD", "active": true, "city": "Detroit", "acceptable_cities": [], "unacceptable_cities": [], "state": "MI", "county": "Wayne County", "timezone": "America/Detroit", "area_codes": ["248", "313"], "world_region": "NA", "country": "US", "lat": "42.3939", "long": "-83.2467"}, "birth": {"day": 17, "month": 7, "year": 1920, "original": "July 17 1920"}, "death": {"day": 13, "month": 12, "year": 1994, "original": "Dec 1994"}}, {"name": {"title": "", "first": "John", "middle": "F", "last": "Jerore", "suffix": "", "nickname": "", "original": "John F Jerore"}, "location": {"zip_code": "48223", "zip_code_type": "STANDARD", "active": true, "city": "Detroit", "acceptable_cities": [], "unacceptable_cities": [], "state": "MI", "county": "Wayne County", "timezone": "America/Detroit", "area_codes": ["248", "313"], "world_region": "NA", "country": "US", "lat": "42.3939", "long": "-83.2467"}, "birth": {"day": 25, "month": 9, "year": 1920, "original": "Sep 25 1920"}, "death": {"day": 26, "month": 6, "year": 1994, "original": "June 26 1994"}}, {"name": {"title": "", "first": "Ellen", "middle": "M", "last": "Phillips", "suffix": "", "nickname": "", "original": "Ellen M Phillips"}, "location": {"zip_code": "48223", "zip_code_type": "STANDARD", "active": true, "city": "Detroit", "acceptable_cities": [], "unacceptable_cities": [], "state": "MI", "county": "Wayne County", "timezone": "America/Detroit", "area_codes": ["248", "313"], "world_region": "NA", "country": "US", "lat": "42.3939", "long": "-83.2467"}, "birth": {"day": 14, "month": 11, "year": 1920, "original": "Nov 14 1920"}, "death": {"day": 13, "month": 10, "year": 1994, "original": "Oct 1994"}}, {"name": {"title": "", "first": "Evelyn", "middle": "", "last": "Coves", "suffix": "", "nickname": "", "original": "Evelyn Coves"}, "location": {"zip_code": "48223", "zip_code_type": "STANDARD", "active": true, "city": "Detroit", "acceptable_cities": [], "unacceptable_cities": [], "state": "MI", "county": "Wayne County", "timezone": "America/Detroit", "area_codes": ["248", "313"], "world_region": "NA", "country": "US", "lat": "42.3939", "long": "-83.2467"}, "birth": {"day": 13, "month": 8, "year": 1920, "original": "Aug 13 1920"}, "death": {"day": 15, "month": 9, "year": 1994, "original": "Sep 15 1994"}}, {"name": {"title": "", "first": "Wallace", "middle": "", "last": "Arnold", "suffix": "", "nickname": "", "original": "Wallace Arnold"}, "location": {"zip_code": "48223", "zip_code_type": "STANDARD", "active": true, "city": "Detroit", "acceptable_cities": [], "unacceptable_cities": [], "state": "MI", "county": "Wayne County", "timezone": "America/Detroit", "area_codes": ["248", "313"], "world_region": "NA", "country": "US", "lat": "42.3939", "long": "-83.2467"}, "birth": {"day": 30, "month": 10, "year": 1920, "original": "Oct 30 1920"}, "death": {"day": 31, "month": 1, "year": 1994, "original": "Jan 31 1994"}}]